LICENSE
MANIFEST.in
README.rst
setup.py
tests.py
Openedoo_Script_Test.egg-info/PKG-INFO
Openedoo_Script_Test.egg-info/SOURCES.txt
Openedoo_Script_Test.egg-info/dependency_links.txt
Openedoo_Script_Test.egg-info/not-zip-safe
Openedoo_Script_Test.egg-info/requires.txt
Openedoo_Script_Test.egg-info/top_level.txt
docs/Makefile
docs/conf.py
docs/index.rst
docs/make.bat
docs/_static/flask-script.png
docs/_static/index.html
docs/_themes/README
docs/_themes/flask_theme_support.py
docs/_themes/flask/theme.conf
docs/_themes/flask/static/flasky.css_t
docs/_themes/flask_small/layout.html
docs/_themes/flask_small/theme.conf
docs/_themes/flask_small/static/flasky.css_t
openedoo_script/__init__.py
openedoo_script/_compat.py
openedoo_script/cli.py
openedoo_script/commands.py