Metadata-Version: 1.1
Name: Openedoo-Script-Test
Version: 0.1.1
Summary: Scripting support for Flask
Home-page: https://github.com/openedoo/openedoo-script
Author: rendiya
Author-email: ligerrendy@gmail.com
License: MIT
Download-URL: https://github.com/openedoo/openedoo-script/archive/master.zip
Platform: any
Classifier: Development Status :: 5 - Production/Stable
Classifier: Environment :: Web Environment
Classifier: Intended Audience :: Developers
Classifier: License :: OSI Approved :: BSD License
Classifier: Operating System :: OS Independent
Classifier: Programming Language :: Python
Classifier: Programming Language :: Python :: 2
Classifier: Programming Language :: Python :: 2.7
Classifier: Programming Language :: Python :: 3
Classifier: Programming Language :: Python :: 3.4
Classifier: Programming Language :: Python :: 3.5
Classifier: Topic :: Internet :: WWW/HTTP :: Dynamic Content
Classifier: Topic :: Software Development :: Libraries :: Python Modules
